{
  "places": [
    {
      "name": "Михайловское",
      "description":
        "Родовое имение матери Пушкина. Здесь поэт отбывал ссылку (1824–1826), написал главы «Евгения Онегина», «Бориса Годунова», лирические стихи. Главное место для погружения в творчество Пушкина.",
      "latitude": 57.060998933492094,
      "longitude": 28.919729029379553
    },
    {
      "name": "Петровское",
      "description":
        "Имение прадеда Пушкина — Абрама Ганнибала. Экспозиция посвящена истории рода Ганнибалов и детству поэта. Восстановлены усадебный дом, парк с липовой аллеей и беседкой.",
      "latitude": 57.077894176598660,
      "longitude": 28.948251089911977
    },
    {
      "name": "Пушкинская деревня",
      "description":
        "Единственный в Псковской области музей деревянного зодчества под открытым небом. Воссоздана деревня пушкинской эпохи. Здесь Пушкин изучал крестьянский быт, что отразилось в «Зимнем вечере» и сказках.",
      "latitude": 57.047019904362930,
      "longitude": 28.915868490089462
    },
    {
      "name": "Тригорское",
      "description":
        "Имение друзей Пушкина — семьи Осиповых-Вульф. Прототип «дома Лариных» из «Евгения Онегина». Сохранились «скамья Онегина», «дуб уединенный», «аллея Татьяны». Место светлых воспоминаний поэта.",
      "latitude": 57.055840304516900,
      "longitude": 28.871791216194026
    },
    {
      "name": "Музей-мельница",
      "description":
        "Действующая водяная мельница XVIII века. Пушкин часто бывал здесь, наблюдал за работой мельников.",
      "latitude": 57.046203050028230,
      "longitude": 28.917429002582402
    },
    {
      "name": "Музейная почта",
      "description":
        "Интерактивный музей в деревне Бугрово. Можно написать письмо пером и чернилами и отправить его, узнать о работе почты в пушкинское время. Дети учатся складывать письма «конвертом-треугольником».",
      "latitude": 57.047723140546620,
      "longitude": 28.915073363687387
    },
    {
      "name": "Святогорский Свято-Успенский монастырь",
      "description":
        "Место упокоения Пушкина. Поэт посещал монастырь для работы в архивах над «Борисом Годуновым». В 1837 году здесь похоронен у алтарной стены Успенского собора. Хранит мемориальные плиты семьи Пушкиных-Ганнибалов.",
      "latitude": 57.022186413075100,
      "longitude": 28.919850377942920
    },
    {
      "name": "Зооград",
      "description":
        "Современный контактный зоопарк в Пушкинских Горах. Дети могут кормить оленей, коз, кроликов. Удобное место для отдыха после экскурсий, особенно с семьей.",
      "latitude": 57.030908036968350,
      "longitude": 28.892865852320757
    },
    {
      "name": "Столетний дуб",
      "description":
        "Легендарный дуб в Михайловском парке, посаженный в XVIII веке. Символ «пушкинского» ландшафта. Встречается в зарисовках поэта о Михайловском.",
      "latitude": 57.060585854624804,
      "longitude": 28.921398260220430
    },
    {
      "name": "Остров Уединения",
      "description":
        "Романтичный уголок в парке Михайловского. Небольшой островок в пруду, соединен с берегом мостиком. По преданию, Пушкин любил здесь читать и размышлять.",
      "latitude": 57.059440128728000,
      "longitude": 28.923010267838380
    },
    {
      "name": "Гостиница Арина Р",
      "description":
        "Современная гостиница в Пушкинских Горах, названная в честь няни поэта. Удобная база для экскурсий: номера в стиле XIX века, ресторан русской кухни. Отсюда легко добраться до всех усадеб.",
      "latitude": 57.041719636123084,
      "longitude": 28.913623082245767
    }
  ],
  "distances": [
    {"row": [0, 4, 1.8, 7.4, 2, 1.8, 6, 4, 0.15, 0.4, 2.5]},
    {"row": [4, 0, 5.9, 11.3, 6.2, 5.9, 7, 8, 3.9, 3.8, 6.5]},
    {"row": [1.8, 5.9, 0, 5.5, 0.2, 0.1, 3.2, 3.2, 1.8, 1.7, 0.9]},
    {"row": [7.4, 11.3, 5.5, 0, 5.4, 5.5, 9, 6, 7.4, 7.3, 6.4]},
    {"row": [1.9, 6.2, 0.2, 5.4, 0, 0.3, 3, 3, 2, 1.9, 0.8]},
    {"row": [1.8, 5.9, 0.1, 5.5, 0.3, 0, 3.3, 3.3, 1.7, 1.6, 1]},
    {"row": [6, 7, 3.2, 9, 3, 3.3, 0, 3, 6, 5.9, 2.7]},
    {"row": [4, 8, 3.2, 6, 3, 3.3, 3, 0, 4, 3.9, 2.3]},
    {"row": [0.15, 3.9, 1.8, 7.4, 2, 1.7, 6, 4, 0, 0.25, 2.5]},
    {"row": [0.4, 3.8, 1.7, 7.3, 1.9, 1.6, 5.9, 3.9, 0.25, 0, 2.4]},
    {"row": [2.5, 6.5, 0.9, 6.4, 0.8, 1, 2.7, 2.3, 2.5, 2.4, 0]}
  ]
}
